[
  {
    "word": "환율",
    "meaning": "이 금융 용어는 두 나라의 화폐 간의 교환 비율을 나타낸다.",
    "is_correct": true
  },
  {
    "word": "금리의 변동",
    "meaning": "이 금융 용어는 경제 상황이나 정책 변화에 따라 자금의 비용이 상승하거나 하락하는 현상을 의미한다.",
    "is_correct": true
  },
  {
    "word": "총소득",
    "meaning": "이 금융 용어는 개인이나 가구가 특정 기간 동안 얻은 모든 수입의 총합을 의미한다.",
    "is_correct": true
  },
  {
    "word": "달러 환율",
    "meaning": "이 금융 용어는 특정 국가의 통화가 다른 국가의 통화와 비교될 때의 가치 변동을 나타낸다.",
    "is_correct": false
  },
  {
    "word": "계약서",
    "meaning": "이 문서는 당사자 간의 합의 내용을 명확히 기록하여 법적 효력을 지니는 중요한 자료이다.",
    "is_correct": true
  },
  {
    "word": "차용증",
    "meaning": "이 금융 용어는 투자자가 주식이나 자산을 매입하기 위해 사용하는 계약서이다.",
    "is_correct": false
  },
  {
    "word": "금융약관",
    "meaning": "이 금융 용어는 상품이나 서비스 이용 시의 조건과 권리, 의무를 구체적으로 규정한 내용을 의미한다.",
    "is_correct": true
  },
  {
    "word": "채무불이행",
    "meaning": "이 금융 용어는 자산의 가치가 급격히 상승하는 상태를 의미한다.",
    "is_correct": false
  },
  {
    "word": "예산 수립",
    "meaning": "이 금융 용어는 과거의 지출을 분석하여 불필요한 비용을 줄이는 전략을 세우는 과정을 의미한다.",
    "is_correct": false
  },
  {
    "word": "금융기관",
    "meaning": "이 금융 용어는 자금의 흐름을 원활하게 하고 다양한 금융 상품과 서비스를 제공하는 기관들을 포함하는 개념이다.",
    "is_correct": true
  }
]